{"nodes":[{"content":"Provides a strongly typed <xref href=\"System.Web.UI.HierarchicalDataSourceView\"></xref> object for the <xref href=\"System.Web.UI.WebControls.SiteMapDataSource\"></xref> control.","nodes":[{"pos":[0,176],"content":"Provides a strongly typed <ph id=\"ph1\">&lt;xref href=\"System.Web.UI.HierarchicalDataSourceView\"&gt;&lt;/xref&gt;</ph> object for the <ph id=\"ph2\">&lt;xref href=\"System.Web.UI.WebControls.SiteMapDataSource\"&gt;&lt;/xref&gt;</ph> control.","source":"Provides a strongly typed <xref href=\"System.Web.UI.HierarchicalDataSourceView\"></xref> object for the <xref href=\"System.Web.UI.WebControls.SiteMapDataSource\"></xref> control."}],"pos":[1026,1203],"yaml":true},{"content":"The <xref:System.Web.UI.WebControls.SiteMapDataSource> control enables ASP.NET data-bound controls, such as the <xref:System.Web.UI.WebControls.TreeView> and <xref:System.Web.UI.WebControls.Menu> controls, to bind to site map data. The <xref:System.Web.UI.WebControls.SiteMapDataSourceView> class is used by controls developers but it is not used by page developers nor in page code.  \n  \n The <xref:System.Web.UI.WebControls.SiteMapDataSource> returns a <xref:System.Web.UI.WebControls.SiteMapDataSourceView> for a specified hierarchical path when the <xref:System.Web.UI.HierarchicalDataSourceView.Select%2A> method is called. Like all hierarchical data source view objects, the <xref:System.Web.UI.WebControls.SiteMapDataSourceView> is not named; rather, its is identified by its unique hierarchical path.  \n  \n The <xref:System.Web.UI.WebControls.SiteMapDataSourceView> is a wrapper class on a <xref:System.Web.SiteMapNodeCollection> collection. The <xref:System.Web.SiteMapNodeCollection> class implements the <xref:System.Web.UI.IHierarchicalEnumerable> interface, which the <xref:System.Web.UI.WebControls.SiteMapDataSourceView> class returns from a call to `Select` method. Because the <xref:System.Web.UI.WebControls.SiteMapDataSource> and <xref:System.Web.UI.WebControls.SiteMapDataSourceView> work with <xref:System.Web.SiteMapNode> objects, the view maintains an internal <xref:System.Web.SiteMapNodeCollection> to contain them. The collection is initialized using the view's constructors and accessed with the <xref:System.Web.UI.WebControls.SiteMapDataSourceView.Select%2A> method.","nodes":[{"pos":[0,383],"content":"The <xref:System.Web.UI.WebControls.SiteMapDataSource> control enables ASP.NET data-bound controls, such as the <xref:System.Web.UI.WebControls.TreeView> and <xref:System.Web.UI.WebControls.Menu> controls, to bind to site map data. The <xref:System.Web.UI.WebControls.SiteMapDataSourceView> class is used by controls developers but it is not used by page developers nor in page code.","nodes":[{"content":"The <xref:System.Web.UI.WebControls.SiteMapDataSource> control enables ASP.NET data-bound controls, such as the <xref:System.Web.UI.WebControls.TreeView> and <xref:System.Web.UI.WebControls.Menu> controls, to bind to site map data. The <xref:System.Web.UI.WebControls.SiteMapDataSourceView> class is used by controls developers but it is not used by page developers nor in page code.","pos":[0,383],"nodes":[{"content":"The <ph id=\"ph1\">&lt;xref:System.Web.UI.WebControls.SiteMapDataSource&gt;</ph> control enables ASP.NET data-bound controls, such as the <ph id=\"ph2\">&lt;xref:System.Web.UI.WebControls.TreeView&gt;</ph> and <ph id=\"ph3\">&lt;xref:System.Web.UI.WebControls.Menu&gt;</ph> controls, to bind to site map data.","pos":[0,231],"source":"The <xref:System.Web.UI.WebControls.SiteMapDataSource> control enables ASP.NET data-bound controls, such as the <xref:System.Web.UI.WebControls.TreeView> and <xref:System.Web.UI.WebControls.Menu> controls, to bind to site map data."},{"content":"The <ph id=\"ph1\">&lt;xref:System.Web.UI.WebControls.SiteMapDataSourceView&gt;</ph> class is used by controls developers but it is not used by page developers nor in page code.","pos":[232,383],"source":" The <xref:System.Web.UI.WebControls.SiteMapDataSourceView> class is used by controls developers but it is not used by page developers nor in page code."}]}]},{"pos":[390,808],"content":"The <xref:System.Web.UI.WebControls.SiteMapDataSource> returns a <xref:System.Web.UI.WebControls.SiteMapDataSourceView> for a specified hierarchical path when the <xref:System.Web.UI.HierarchicalDataSourceView.Select%2A> method is called. Like all hierarchical data source view objects, the <xref:System.Web.UI.WebControls.SiteMapDataSourceView> is not named; rather, its is identified by its unique hierarchical path.","nodes":[{"content":"The <xref:System.Web.UI.WebControls.SiteMapDataSource> returns a <xref:System.Web.UI.WebControls.SiteMapDataSourceView> for a specified hierarchical path when the <xref:System.Web.UI.HierarchicalDataSourceView.Select%2A> method is called. Like all hierarchical data source view objects, the <xref:System.Web.UI.WebControls.SiteMapDataSourceView> is not named; rather, its is identified by its unique hierarchical path.","pos":[0,418],"nodes":[{"content":"The <ph id=\"ph1\">&lt;xref:System.Web.UI.WebControls.SiteMapDataSource&gt;</ph> returns a <ph id=\"ph2\">&lt;xref:System.Web.UI.WebControls.SiteMapDataSourceView&gt;</ph> for a specified hierarchical path when the <ph id=\"ph3\">&lt;xref:System.Web.UI.HierarchicalDataSourceView.Select%2A&gt;</ph> method is called.","pos":[0,238],"source":"The <xref:System.Web.UI.WebControls.SiteMapDataSource> returns a <xref:System.Web.UI.WebControls.SiteMapDataSourceView> for a specified hierarchical path when the <xref:System.Web.UI.HierarchicalDataSourceView.Select%2A> method is called."},{"content":"Like all hierarchical data source view objects, the <ph id=\"ph1\">&lt;xref:System.Web.UI.WebControls.SiteMapDataSourceView&gt;</ph> is not named; rather, its is identified by its unique hierarchical path.","pos":[239,418],"source":" Like all hierarchical data source view objects, the <xref:System.Web.UI.WebControls.SiteMapDataSourceView> is not named; rather, its is identified by its unique hierarchical path."}]}]},{"pos":[815,1595],"content":"The <xref:System.Web.UI.WebControls.SiteMapDataSourceView> is a wrapper class on a <xref:System.Web.SiteMapNodeCollection> collection. The <xref:System.Web.SiteMapNodeCollection> class implements the <xref:System.Web.UI.IHierarchicalEnumerable> interface, which the <xref:System.Web.UI.WebControls.SiteMapDataSourceView> class returns from a call to `Select` method. Because the <xref:System.Web.UI.WebControls.SiteMapDataSource> and <xref:System.Web.UI.WebControls.SiteMapDataSourceView> work with <xref:System.Web.SiteMapNode> objects, the view maintains an internal <xref:System.Web.SiteMapNodeCollection> to contain them. The collection is initialized using the view's constructors and accessed with the <xref:System.Web.UI.WebControls.SiteMapDataSourceView.Select%2A> method.","nodes":[{"content":"The <ph id=\"ph1\">&lt;xref:System.Web.UI.WebControls.SiteMapDataSourceView&gt;</ph> is a wrapper class on a <ph id=\"ph2\">&lt;xref:System.Web.SiteMapNodeCollection&gt;</ph> collection.","pos":[0,134],"source":"The <xref:System.Web.UI.WebControls.SiteMapDataSourceView> is a wrapper class on a <xref:System.Web.SiteMapNodeCollection> collection."},{"content":"The <ph id=\"ph1\">&lt;xref:System.Web.SiteMapNodeCollection&gt;</ph> class implements the <ph id=\"ph2\">&lt;xref:System.Web.UI.IHierarchicalEnumerable&gt;</ph> interface, which the <ph id=\"ph3\">&lt;xref:System.Web.UI.WebControls.SiteMapDataSourceView&gt;</ph> class returns from a call to <ph id=\"ph4\">`Select`</ph> method.","pos":[135,366],"source":" The <xref:System.Web.SiteMapNodeCollection> class implements the <xref:System.Web.UI.IHierarchicalEnumerable> interface, which the <xref:System.Web.UI.WebControls.SiteMapDataSourceView> class returns from a call to `Select` method."},{"content":"Because the <ph id=\"ph1\">&lt;xref:System.Web.UI.WebControls.SiteMapDataSource&gt;</ph> and <ph id=\"ph2\">&lt;xref:System.Web.UI.WebControls.SiteMapDataSourceView&gt;</ph> work with <ph id=\"ph3\">&lt;xref:System.Web.SiteMapNode&gt;</ph> objects, the view maintains an internal <ph id=\"ph4\">&lt;xref:System.Web.SiteMapNodeCollection&gt;</ph> to contain them.","pos":[367,625],"source":" Because the <xref:System.Web.UI.WebControls.SiteMapDataSource> and <xref:System.Web.UI.WebControls.SiteMapDataSourceView> work with <xref:System.Web.SiteMapNode> objects, the view maintains an internal <xref:System.Web.SiteMapNodeCollection> to contain them."},{"content":"The collection is initialized using the view's constructors and accessed with the <ph id=\"ph1\">&lt;xref:System.Web.UI.WebControls.SiteMapDataSourceView.Select%2A&gt;</ph> method.","pos":[626,780],"source":" The collection is initialized using the view's constructors and accessed with the <xref:System.Web.UI.WebControls.SiteMapDataSourceView.Select%2A> method."}]}],"pos":[1214,2816],"yaml":true,"extradata":"MT"},{"content":"Initializes a new named instance of the <xref href=\"System.Web.UI.WebControls.SiteMapDataSourceView\"></xref> class, adding the single specified node to the internal collection of nodes.","nodes":[{"pos":[0,185],"content":"Initializes a new named instance of the <ph id=\"ph1\">&lt;xref href=\"System.Web.UI.WebControls.SiteMapDataSourceView\"&gt;&lt;/xref&gt;</ph> class, adding the single specified node to the internal collection of nodes.","source":"Initializes a new named instance of the <xref href=\"System.Web.UI.WebControls.SiteMapDataSourceView\"></xref> class, adding the single specified node to the internal collection of nodes."}],"pos":[6406,6592],"yaml":true},{"content":"The <xref:System.Web.UI.WebControls.SiteMapDataSourceView> class is a wrapper class on a <xref:System.Web.SiteMapNodeCollection> object. Creating a <xref:System.Web.UI.WebControls.SiteMapDataSourceView> using the <xref:System.Web.UI.WebControls.SiteMapDataSourceView.%23ctor%2A> constructor initializes the internal node collection with a single <xref:System.Web.SiteMapNode> object. The site map structure is navigated using the node as a point of reference.","nodes":[{"pos":[0,459],"content":"The <xref:System.Web.UI.WebControls.SiteMapDataSourceView> class is a wrapper class on a <xref:System.Web.SiteMapNodeCollection> object. Creating a <xref:System.Web.UI.WebControls.SiteMapDataSourceView> using the <xref:System.Web.UI.WebControls.SiteMapDataSourceView.%23ctor%2A> constructor initializes the internal node collection with a single <xref:System.Web.SiteMapNode> object. The site map structure is navigated using the node as a point of reference.","nodes":[{"content":"The <xref:System.Web.UI.WebControls.SiteMapDataSourceView> class is a wrapper class on a <xref:System.Web.SiteMapNodeCollection> object. Creating a <xref:System.Web.UI.WebControls.SiteMapDataSourceView> using the <xref:System.Web.UI.WebControls.SiteMapDataSourceView.%23ctor%2A> constructor initializes the internal node collection with a single <xref:System.Web.SiteMapNode> object. The site map structure is navigated using the node as a point of reference.","pos":[0,459],"nodes":[{"content":"The <ph id=\"ph1\">&lt;xref:System.Web.UI.WebControls.SiteMapDataSourceView&gt;</ph> class is a wrapper class on a <ph id=\"ph2\">&lt;xref:System.Web.SiteMapNodeCollection&gt;</ph> object.","pos":[0,136],"source":"The <xref:System.Web.UI.WebControls.SiteMapDataSourceView> class is a wrapper class on a <xref:System.Web.SiteMapNodeCollection> object."},{"content":"Creating a <ph id=\"ph1\">&lt;xref:System.Web.UI.WebControls.SiteMapDataSourceView&gt;</ph> using the <ph id=\"ph2\">&lt;xref:System.Web.UI.WebControls.SiteMapDataSourceView.%23ctor%2A&gt;</ph> constructor initializes the internal node collection with a single <ph id=\"ph3\">&lt;xref:System.Web.SiteMapNode&gt;</ph> object.","pos":[137,383],"source":" Creating a <xref:System.Web.UI.WebControls.SiteMapDataSourceView> using the <xref:System.Web.UI.WebControls.SiteMapDataSourceView.%23ctor%2A> constructor initializes the internal node collection with a single <xref:System.Web.SiteMapNode> object."},{"content":"The site map structure is navigated using the node as a point of reference.","pos":[384,459]}]}]}],"pos":[6603,7063],"yaml":true,"extradata":"MT"},{"content":"The <xref href=\"System.Web.UI.WebControls.SiteMapDataSource\"></xref> that the <xref href=\"System.Web.UI.WebControls.SiteMapDataSourceView\"></xref> is associated with.","nodes":[{"pos":[0,166],"content":"The <ph id=\"ph1\">&lt;xref href=\"System.Web.UI.WebControls.SiteMapDataSource\"&gt;&lt;/xref&gt;</ph> that the <ph id=\"ph2\">&lt;xref href=\"System.Web.UI.WebControls.SiteMapDataSourceView\"&gt;&lt;/xref&gt;</ph> is associated with.","source":"The <xref href=\"System.Web.UI.WebControls.SiteMapDataSource\"></xref> that the <xref href=\"System.Web.UI.WebControls.SiteMapDataSourceView\"></xref> is associated with."}],"pos":[7317,7484],"yaml":true},{"content":"The name of the view.","nodes":[{"pos":[0,21],"content":"The name of the view.","nodes":[{"content":"The name of the view.","pos":[0,21]}]}],"pos":[7544,7566],"yaml":true},{"content":"The <xref href=\"System.Web.SiteMapNode\"></xref> to add to the internal <xref href=\"System.Web.SiteMapNodeCollection\"></xref>.","nodes":[{"pos":[0,125],"content":"The <ph id=\"ph1\">&lt;xref href=\"System.Web.SiteMapNode\"&gt;&lt;/xref&gt;</ph> to add to the internal <ph id=\"ph2\">&lt;xref href=\"System.Web.SiteMapNodeCollection\"&gt;&lt;/xref&gt;</ph>.","source":"The <xref href=\"System.Web.SiteMapNode\"></xref> to add to the internal <xref href=\"System.Web.SiteMapNodeCollection\"></xref>."}],"pos":[7635,7761],"yaml":true},{"content":"Initializes a new named instance of the <xref href=\"System.Web.UI.WebControls.SiteMapDataSourceView\"></xref> class, setting the internal collection of nodes to the specified node collection.","nodes":[{"pos":[0,190],"content":"Initializes a new named instance of the <ph id=\"ph1\">&lt;xref href=\"System.Web.UI.WebControls.SiteMapDataSourceView\"&gt;&lt;/xref&gt;</ph> class, setting the internal collection of nodes to the specified node collection.","source":"Initializes a new named instance of the <xref href=\"System.Web.UI.WebControls.SiteMapDataSourceView\"></xref> class, setting the internal collection of nodes to the specified node collection."}],"pos":[9266,9457],"yaml":true},{"content":"The <xref:System.Web.UI.WebControls.SiteMapDataSourceView> class is a wrapper class on a <xref:System.Web.SiteMapNodeCollection> object. Creating a <xref:System.Web.UI.WebControls.SiteMapDataSourceView> using the <xref:System.Web.UI.WebControls.SiteMapDataSourceView.%23ctor%2A> constructor initializes the internal node collection with the <xref:System.Web.SiteMapNodeCollection> that is passed to the constructor.","nodes":[{"pos":[0,415],"content":"The <xref:System.Web.UI.WebControls.SiteMapDataSourceView> class is a wrapper class on a <xref:System.Web.SiteMapNodeCollection> object. Creating a <xref:System.Web.UI.WebControls.SiteMapDataSourceView> using the <xref:System.Web.UI.WebControls.SiteMapDataSourceView.%23ctor%2A> constructor initializes the internal node collection with the <xref:System.Web.SiteMapNodeCollection> that is passed to the constructor.","nodes":[{"content":"The <xref:System.Web.UI.WebControls.SiteMapDataSourceView> class is a wrapper class on a <xref:System.Web.SiteMapNodeCollection> object. Creating a <xref:System.Web.UI.WebControls.SiteMapDataSourceView> using the <xref:System.Web.UI.WebControls.SiteMapDataSourceView.%23ctor%2A> constructor initializes the internal node collection with the <xref:System.Web.SiteMapNodeCollection> that is passed to the constructor.","pos":[0,415],"nodes":[{"content":"The <ph id=\"ph1\">&lt;xref:System.Web.UI.WebControls.SiteMapDataSourceView&gt;</ph> class is a wrapper class on a <ph id=\"ph2\">&lt;xref:System.Web.SiteMapNodeCollection&gt;</ph> object.","pos":[0,136],"source":"The <xref:System.Web.UI.WebControls.SiteMapDataSourceView> class is a wrapper class on a <xref:System.Web.SiteMapNodeCollection> object."},{"content":"Creating a <ph id=\"ph1\">&lt;xref:System.Web.UI.WebControls.SiteMapDataSourceView&gt;</ph> using the <ph id=\"ph2\">&lt;xref:System.Web.UI.WebControls.SiteMapDataSourceView.%23ctor%2A&gt;</ph> constructor initializes the internal node collection with the <ph id=\"ph3\">&lt;xref:System.Web.SiteMapNodeCollection&gt;</ph> that is passed to the constructor.","pos":[137,415],"source":" Creating a <xref:System.Web.UI.WebControls.SiteMapDataSourceView> using the <xref:System.Web.UI.WebControls.SiteMapDataSourceView.%23ctor%2A> constructor initializes the internal node collection with the <xref:System.Web.SiteMapNodeCollection> that is passed to the constructor."}]}]}],"pos":[9468,9884],"yaml":true,"extradata":"MT"},{"content":"The <xref href=\"System.Web.UI.WebControls.SiteMapDataSource\"></xref> that the <xref href=\"System.Web.UI.WebControls.SiteMapDataSourceView\"></xref> is associated with.","nodes":[{"pos":[0,166],"content":"The <ph id=\"ph1\">&lt;xref href=\"System.Web.UI.WebControls.SiteMapDataSource\"&gt;&lt;/xref&gt;</ph> that the <ph id=\"ph2\">&lt;xref href=\"System.Web.UI.WebControls.SiteMapDataSourceView\"&gt;&lt;/xref&gt;</ph> is associated with.","source":"The <xref href=\"System.Web.UI.WebControls.SiteMapDataSource\"></xref> that the <xref href=\"System.Web.UI.WebControls.SiteMapDataSourceView\"></xref> is associated with."}],"pos":[10154,10321],"yaml":true},{"content":"The name of the view.","nodes":[{"pos":[0,21],"content":"The name of the view.","nodes":[{"content":"The name of the view.","pos":[0,21]}]}],"pos":[10381,10403],"yaml":true},{"content":"A <xref href=\"System.Web.SiteMapNodeCollection\"></xref> of nodes that the <xref href=\"System.Web.UI.WebControls.SiteMapDataSourceView\"></xref> provides a view of.","nodes":[{"pos":[0,162],"content":"A <ph id=\"ph1\">&lt;xref href=\"System.Web.SiteMapNodeCollection\"&gt;&lt;/xref&gt;</ph> of nodes that the <ph id=\"ph2\">&lt;xref href=\"System.Web.UI.WebControls.SiteMapDataSourceView\"&gt;&lt;/xref&gt;</ph> provides a view of.","source":"A <xref href=\"System.Web.SiteMapNodeCollection\"></xref> of nodes that the <xref href=\"System.Web.UI.WebControls.SiteMapDataSourceView\"></xref> provides a view of."}],"pos":[10488,10651],"yaml":true},{"content":"Gets the collection of the <xref href=\"System.Web.SiteMapNode\"></xref> objects that represents the site navigation structure for the current user.","nodes":[{"pos":[0,146],"content":"Gets the collection of the <ph id=\"ph1\">&lt;xref href=\"System.Web.SiteMapNode\"&gt;&lt;/xref&gt;</ph> objects that represents the site navigation structure for the current user.","source":"Gets the collection of the <xref href=\"System.Web.SiteMapNode\"></xref> objects that represents the site navigation structure for the current user."}],"pos":[11927,12074],"yaml":true},{"content":"The <xref:System.Web.UI.WebControls.SiteMapDataSourceView> class implements the inherited <xref:System.Web.UI.WebControls.SiteMapDataSourceView.ExecuteSelect%2A> method to retrieve a set of nodes that represents the site navigation structure for the current ASP.NET application. Page developers and data-bound control authors do not call the <xref:System.Web.UI.WebControls.SiteMapDataSourceView.ExecuteSelect%2A> method directly; instead, use the publicly exposed <xref:System.Web.UI.WebControls.SiteMapDataSourceView.Select%2A> method.","nodes":[{"pos":[0,537],"content":"The <xref:System.Web.UI.WebControls.SiteMapDataSourceView> class implements the inherited <xref:System.Web.UI.WebControls.SiteMapDataSourceView.ExecuteSelect%2A> method to retrieve a set of nodes that represents the site navigation structure for the current ASP.NET application. Page developers and data-bound control authors do not call the <xref:System.Web.UI.WebControls.SiteMapDataSourceView.ExecuteSelect%2A> method directly; instead, use the publicly exposed <xref:System.Web.UI.WebControls.SiteMapDataSourceView.Select%2A> method.","nodes":[{"content":"The <xref:System.Web.UI.WebControls.SiteMapDataSourceView> class implements the inherited <xref:System.Web.UI.WebControls.SiteMapDataSourceView.ExecuteSelect%2A> method to retrieve a set of nodes that represents the site navigation structure for the current ASP.NET application. Page developers and data-bound control authors do not call the <xref:System.Web.UI.WebControls.SiteMapDataSourceView.ExecuteSelect%2A> method directly; instead, use the publicly exposed <xref:System.Web.UI.WebControls.SiteMapDataSourceView.Select%2A> method.","pos":[0,537],"nodes":[{"content":"The <ph id=\"ph1\">&lt;xref:System.Web.UI.WebControls.SiteMapDataSourceView&gt;</ph> class implements the inherited <ph id=\"ph2\">&lt;xref:System.Web.UI.WebControls.SiteMapDataSourceView.ExecuteSelect%2A&gt;</ph> method to retrieve a set of nodes that represents the site navigation structure for the current ASP.NET application.","pos":[0,278],"source":"The <xref:System.Web.UI.WebControls.SiteMapDataSourceView> class implements the inherited <xref:System.Web.UI.WebControls.SiteMapDataSourceView.ExecuteSelect%2A> method to retrieve a set of nodes that represents the site navigation structure for the current ASP.NET application."},{"content":"Page developers and data-bound control authors do not call the <ph id=\"ph1\">&lt;xref:System.Web.UI.WebControls.SiteMapDataSourceView.ExecuteSelect%2A&gt;</ph> method directly; instead, use the publicly exposed <ph id=\"ph2\">&lt;xref:System.Web.UI.WebControls.SiteMapDataSourceView.Select%2A&gt;</ph> method.","pos":[279,537],"source":" Page developers and data-bound control authors do not call the <xref:System.Web.UI.WebControls.SiteMapDataSourceView.ExecuteSelect%2A> method directly; instead, use the publicly exposed <xref:System.Web.UI.WebControls.SiteMapDataSourceView.Select%2A> method."}]}]}],"pos":[12085,12623],"yaml":true,"extradata":"MT"},{"content":"A <xref href=\"System.Web.UI.DataSourceSelectArguments\"></xref> that is used to request operations on the data beyond basic data retrieval.","nodes":[{"pos":[0,138],"content":"A <ph id=\"ph1\">&lt;xref href=\"System.Web.UI.DataSourceSelectArguments\"&gt;&lt;/xref&gt;</ph> that is used to request operations on the data beyond basic data retrieval.","source":"A <xref href=\"System.Web.UI.DataSourceSelectArguments\"></xref> that is used to request operations on the data beyond basic data retrieval."}],"pos":[12870,13009],"yaml":true},{"content":"A <xref href=\"System.Web.SiteMapNodeCollection\"></xref> that represents the site navigation structure for the current user.","nodes":[{"pos":[0,123],"content":"A <ph id=\"ph1\">&lt;xref href=\"System.Web.SiteMapNodeCollection\"&gt;&lt;/xref&gt;</ph> that represents the site navigation structure for the current user.","source":"A <xref href=\"System.Web.SiteMapNodeCollection\"></xref> that represents the site navigation structure for the current user."}],"pos":[13083,13207],"yaml":true},{"content":"The <code>arguments</code> passed to the <xref href=\"System.Web.UI.WebControls.SiteMapDataSourceView.Select(System.Web.UI.DataSourceSelectArguments)\"></xref> specify that the data source should perform some additional work while retrieving data to enable paging or sorting through the retrieved data, but the data source control does not support the requested capability.","nodes":[{"pos":[0,371],"content":"The <bpt id=\"p1\">&lt;code&gt;</bpt><ph id=\"ph1\">arguments</ph><ept id=\"p1\">&lt;/code&gt;</ept> passed to the <ph id=\"ph2\">&lt;xref href=\"System.Web.UI.WebControls.SiteMapDataSourceView.Select(System.Web.UI.DataSourceSelectArguments)\"&gt;&lt;/xref&gt;</ph> specify that the data source should perform some additional work while retrieving data to enable paging or sorting through the retrieved data, but the data source control does not support the requested capability.","source":"The <code>arguments</code> passed to the <xref href=\"System.Web.UI.WebControls.SiteMapDataSourceView.Select(System.Web.UI.DataSourceSelectArguments)\"></xref> specify that the data source should perform some additional work while retrieving data to enable paging or sorting through the retrieved data, but the data source control does not support the requested capability."}],"pos":[13398,13770],"yaml":true},{"content":"Raises the <xref href=\"System.Web.UI.DataSourceView.DataSourceViewChanged\"></xref> event.","nodes":[{"pos":[0,89],"content":"Raises the <ph id=\"ph1\">&lt;xref href=\"System.Web.UI.DataSourceView.DataSourceViewChanged\"&gt;&lt;/xref&gt;</ph> event.","source":"Raises the <xref href=\"System.Web.UI.DataSourceView.DataSourceViewChanged\"></xref> event."}],"pos":[14905,14995],"yaml":true},{"content":"An <xref href=\"System.EventArgs\"></xref> that contains event data.","nodes":[{"pos":[0,66],"content":"An <ph id=\"ph1\">&lt;xref href=\"System.EventArgs\"&gt;&lt;/xref&gt;</ph> that contains event data.","source":"An <xref href=\"System.EventArgs\"></xref> that contains event data."}],"pos":[15157,15224],"yaml":true},{"content":"Gets the collection of the <xref href=\"System.Web.SiteMapNode\"></xref> objects that represents the site navigation structure for the current user.","nodes":[{"pos":[0,146],"content":"Gets the collection of the <ph id=\"ph1\">&lt;xref href=\"System.Web.SiteMapNode\"&gt;&lt;/xref&gt;</ph> objects that represents the site navigation structure for the current user.","source":"Gets the collection of the <xref href=\"System.Web.SiteMapNode\"></xref> objects that represents the site navigation structure for the current user."}],"pos":[16476,16623],"yaml":true},{"content":"The <xref:System.Web.UI.WebControls.SiteMapDataSourceView.Select%2A> method calls the <xref:System.Web.UI.WebControls.SiteMapDataSourceView.ExecuteSelect%2A> method, passing the `arguments` parameter. The <xref:System.Web.UI.WebControls.SiteMapDataSourceView.Select%2A> method is used by controls developers but it is not used by page developers nor in page code.","nodes":[{"pos":[0,363],"content":"The <xref:System.Web.UI.WebControls.SiteMapDataSourceView.Select%2A> method calls the <xref:System.Web.UI.WebControls.SiteMapDataSourceView.ExecuteSelect%2A> method, passing the `arguments` parameter. The <xref:System.Web.UI.WebControls.SiteMapDataSourceView.Select%2A> method is used by controls developers but it is not used by page developers nor in page code.","nodes":[{"content":"The <ph id=\"ph1\">&lt;xref:System.Web.UI.WebControls.SiteMapDataSourceView.Select%2A&gt;</ph> method calls the <ph id=\"ph2\">&lt;xref:System.Web.UI.WebControls.SiteMapDataSourceView.ExecuteSelect%2A&gt;</ph> method, passing the <ph id=\"ph3\">`arguments`</ph> parameter.","pos":[0,200],"source":"The <xref:System.Web.UI.WebControls.SiteMapDataSourceView.Select%2A> method calls the <xref:System.Web.UI.WebControls.SiteMapDataSourceView.ExecuteSelect%2A> method, passing the `arguments` parameter."},{"content":"The <ph id=\"ph1\">&lt;xref:System.Web.UI.WebControls.SiteMapDataSourceView.Select%2A&gt;</ph> method is used by controls developers but it is not used by page developers nor in page code.","pos":[201,363],"source":" The <xref:System.Web.UI.WebControls.SiteMapDataSourceView.Select%2A> method is used by controls developers but it is not used by page developers nor in page code."}]}],"pos":[16634,16998],"yaml":true,"extradata":"MT"},{"content":"A <xref href=\"System.Web.UI.DataSourceSelectArguments\"></xref> that is used to request operations on the data beyond basic data retrieval.","nodes":[{"pos":[0,138],"content":"A <ph id=\"ph1\">&lt;xref href=\"System.Web.UI.DataSourceSelectArguments\"&gt;&lt;/xref&gt;</ph> that is used to request operations on the data beyond basic data retrieval.","source":"A <xref href=\"System.Web.UI.DataSourceSelectArguments\"></xref> that is used to request operations on the data beyond basic data retrieval."}],"pos":[17226,17365],"yaml":true},{"content":"A <xref href=\"System.Web.SiteMapNodeCollection\"></xref> that represents the site navigation structure for the current user.","nodes":[{"pos":[0,123],"content":"A <ph id=\"ph1\">&lt;xref href=\"System.Web.SiteMapNodeCollection\"&gt;&lt;/xref&gt;</ph> that represents the site navigation structure for the current user.","source":"A <xref href=\"System.Web.SiteMapNodeCollection\"></xref> that represents the site navigation structure for the current user."}],"pos":[17439,17563],"yaml":true},{"content":"The <code>arguments</code> passed to the <xref href=\"System.Web.UI.WebControls.SiteMapDataSourceView.Select(System.Web.UI.DataSourceSelectArguments)\"></xref> specify that the data source should perform some additional work while retrieving data to enable paging or sorting through the retrieved data, but the data source control does not support the requested capability.","nodes":[{"pos":[0,371],"content":"The <bpt id=\"p1\">&lt;code&gt;</bpt><ph id=\"ph1\">arguments</ph><ept id=\"p1\">&lt;/code&gt;</ept> passed to the <ph id=\"ph2\">&lt;xref href=\"System.Web.UI.WebControls.SiteMapDataSourceView.Select(System.Web.UI.DataSourceSelectArguments)\"&gt;&lt;/xref&gt;</ph> specify that the data source should perform some additional work while retrieving data to enable paging or sorting through the retrieved data, but the data source control does not support the requested capability.","source":"The <code>arguments</code> passed to the <xref href=\"System.Web.UI.WebControls.SiteMapDataSourceView.Select(System.Web.UI.DataSourceSelectArguments)\"></xref> specify that the data source should perform some additional work while retrieving data to enable paging or sorting through the retrieved data, but the data source control does not support the requested capability."}],"pos":[17747,18119],"yaml":true}],"content":"### YamlMime:ManagedReference\nitems:\n- uid: System.Web.UI.WebControls.SiteMapDataSourceView\n  commentId: T:System.Web.UI.WebControls.SiteMapDataSourceView\n  id: SiteMapDataSourceView\n  children:\n  - System.Web.UI.WebControls.SiteMapDataSourceView.#ctor(System.Web.UI.WebControls.SiteMapDataSource,System.String,System.Web.SiteMapNode)\n  - System.Web.UI.WebControls.SiteMapDataSourceView.#ctor(System.Web.UI.WebControls.SiteMapDataSource,System.String,System.Web.SiteMapNodeCollection)\n  - System.Web.UI.WebControls.SiteMapDataSourceView.ExecuteSelect(System.Web.UI.DataSourceSelectArguments)\n  - System.Web.UI.WebControls.SiteMapDataSourceView.OnDataSourceViewChanged(System.EventArgs)\n  - System.Web.UI.WebControls.SiteMapDataSourceView.Select(System.Web.UI.DataSourceSelectArguments)\n  langs:\n  - csharp\n  name: SiteMapDataSourceView\n  nameWithType: SiteMapDataSourceView\n  fullName: System.Web.UI.WebControls.SiteMapDataSourceView\n  type: Class\n  assemblies:\n  - System.Web\n  namespace: System.Web.UI.WebControls\n  summary: Provides a strongly typed <xref href=\"System.Web.UI.HierarchicalDataSourceView\"></xref> object for the <xref href=\"System.Web.UI.WebControls.SiteMapDataSource\"></xref> control.\n  remarks: \"The <xref:System.Web.UI.WebControls.SiteMapDataSource> control enables ASP.NET data-bound controls, such as the <xref:System.Web.UI.WebControls.TreeView> and <xref:System.Web.UI.WebControls.Menu> controls, to bind to site map data. The <xref:System.Web.UI.WebControls.SiteMapDataSourceView> class is used by controls developers but it is not used by page developers nor in page code.  \\n  \\n The <xref:System.Web.UI.WebControls.SiteMapDataSource> returns a <xref:System.Web.UI.WebControls.SiteMapDataSourceView> for a specified hierarchical path when the <xref:System.Web.UI.HierarchicalDataSourceView.Select%2A> method is called. Like all hierarchical data source view objects, the <xref:System.Web.UI.WebControls.SiteMapDataSourceView> is not named; rather, its is identified by its unique hierarchical path.  \\n  \\n The <xref:System.Web.UI.WebControls.SiteMapDataSourceView> is a wrapper class on a <xref:System.Web.SiteMapNodeCollection> collection. The <xref:System.Web.SiteMapNodeCollection> class implements the <xref:System.Web.UI.IHierarchicalEnumerable> interface, which the <xref:System.Web.UI.WebControls.SiteMapDataSourceView> class returns from a call to `Select` method. Because the <xref:System.Web.UI.WebControls.SiteMapDataSource> and <xref:System.Web.UI.WebControls.SiteMapDataSourceView> work with <xref:System.Web.SiteMapNode> objects, the view maintains an internal <xref:System.Web.SiteMapNodeCollection> to contain them. The collection is initialized using the view's constructors and accessed with the <xref:System.Web.UI.WebControls.SiteMapDataSourceView.Select%2A> method.\"\n  syntax:\n    content: 'public class SiteMapDataSourceView : System.Web.UI.DataSourceView'\n  inheritance:\n  - System.Object\n  - System.Web.UI.DataSourceView\n  implements: []\n  inheritedMembers:\n  - System.Object.Equals(System.Object)\n  - System.Object.Equals(System.Object,System.Object)\n  - System.Object.GetHashCode\n  - System.Object.GetType\n  - System.Object.MemberwiseClone\n  - System.Object.ReferenceEquals(System.Object,System.Object)\n  - System.Object.ToString\n  - System.Web.UI.DataSourceView.CanDelete\n  - System.Web.UI.DataSourceView.CanExecute(System.String)\n  - System.Web.UI.DataSourceView.CanInsert\n  - System.Web.UI.DataSourceView.CanPage\n  - System.Web.UI.DataSourceView.CanRetrieveTotalRowCount\n  - System.Web.UI.DataSourceView.CanSort\n  - System.Web.UI.DataSourceView.CanUpdate\n  - System.Web.UI.DataSourceView.DataSourceViewChanged\n  - System.Web.UI.DataSourceView.Delete(System.Collections.IDictionary,System.Collections.IDictionary,System.Web.UI.DataSourceViewOperationCallback)\n  - System.Web.UI.DataSourceView.Events\n  - System.Web.UI.DataSourceView.ExecuteCommand(System.String,System.Collections.IDictionary,System.Collections.IDictionary)\n  - System.Web.UI.DataSourceView.ExecuteCommand(System.String,System.Collections.IDictionary,System.Collections.IDictionary,System.Web.UI.DataSourceViewOperationCallback)\n  - System.Web.UI.DataSourceView.ExecuteDelete(System.Collections.IDictionary,System.Collections.IDictionary)\n  - System.Web.UI.DataSourceView.ExecuteInsert(System.Collections.IDictionary)\n  - System.Web.UI.DataSourceView.ExecuteUpdate(System.Collections.IDictionary,System.Collections.IDictionary,System.Collections.IDictionary)\n  - System.Web.UI.DataSourceView.Insert(System.Collections.IDictionary,System.Web.UI.DataSourceViewOperationCallback)\n  - System.Web.UI.DataSourceView.Name\n  - System.Web.UI.DataSourceView.RaiseUnsupportedCapabilityError(System.Web.UI.DataSourceCapabilities)\n  - System.Web.UI.DataSourceView.Select(System.Web.UI.DataSourceSelectArguments,System.Web.UI.DataSourceViewSelectCallback)\n  - System.Web.UI.DataSourceView.Update(System.Collections.IDictionary,System.Collections.IDictionary,System.Collections.IDictionary,System.Web.UI.DataSourceViewOperationCallback)\n  version:\n  - netframework-4.5.1\n  - netframework-4.5.2\n  - netframework-4.5\n  - netframework-4.6.1\n  - netframework-4.6.2\n  - netframework-4.6\n  - netframework-4.7\n  monikers:\n  - netframework-4.5.1\n  - netframework-4.5.2\n  - netframework-4.5\n  - netframework-4.6.1\n  - netframework-4.6.2\n  - netframework-4.6\n  - netframework-4.7\n  content_git_url: https://github.com/dotnet/docs/blob/master/xml/System.Web.UI.WebControls/SiteMapDataSourceView.xml\n  ms.technology:\n  - dotnet-webforms\n  ms.author: riande\n  manager: wpickett\n- uid: System.Web.UI.WebControls.SiteMapDataSourceView.#ctor(System.Web.UI.WebControls.SiteMapDataSource,System.String,System.Web.SiteMapNode)\n  commentId: M:System.Web.UI.WebControls.SiteMapDataSourceView.#ctor(System.Web.UI.WebControls.SiteMapDataSource,System.String,System.Web.SiteMapNode)\n  id: '#ctor(System.Web.UI.WebControls.SiteMapDataSource,System.String,System.Web.SiteMapNode)'\n  parent: System.Web.UI.WebControls.SiteMapDataSourceView\n  langs:\n  - csharp\n  name: SiteMapDataSourceView(SiteMapDataSource, String, SiteMapNode)\n  nameWithType: SiteMapDataSourceView.SiteMapDataSourceView(SiteMapDataSource, String, SiteMapNode)\n  fullName: SiteMapDataSourceView.SiteMapDataSourceView(SiteMapDataSource, String, SiteMapNode)\n  type: Constructor\n  assemblies:\n  - System.Web\n  namespace: System.Web.UI.WebControls\n  summary: Initializes a new named instance of the <xref href=\"System.Web.UI.WebControls.SiteMapDataSourceView\"></xref> class, adding the single specified node to the internal collection of nodes.\n  remarks: The <xref:System.Web.UI.WebControls.SiteMapDataSourceView> class is a wrapper class on a <xref:System.Web.SiteMapNodeCollection> object. Creating a <xref:System.Web.UI.WebControls.SiteMapDataSourceView> using the <xref:System.Web.UI.WebControls.SiteMapDataSourceView.%23ctor%2A> constructor initializes the internal node collection with a single <xref:System.Web.SiteMapNode> object. The site map structure is navigated using the node as a point of reference.\n  syntax:\n    content: public SiteMapDataSourceView (System.Web.UI.WebControls.SiteMapDataSource owner, string name, System.Web.SiteMapNode node);\n    parameters:\n    - id: owner\n      type: System.Web.UI.WebControls.SiteMapDataSource\n      description: The <xref href=\"System.Web.UI.WebControls.SiteMapDataSource\"></xref> that the <xref href=\"System.Web.UI.WebControls.SiteMapDataSourceView\"></xref> is associated with.\n    - id: name\n      type: System.String\n      description: The name of the view.\n    - id: node\n      type: System.Web.SiteMapNode\n      description: The <xref href=\"System.Web.SiteMapNode\"></xref> to add to the internal <xref href=\"System.Web.SiteMapNodeCollection\"></xref>.\n  overload: System.Web.UI.WebControls.SiteMapDataSourceView.#ctor*\n  exceptions: []\n  version:\n  - netframework-4.5.1\n  - netframework-4.5.2\n  - netframework-4.5\n  - netframework-4.6.1\n  - netframework-4.6.2\n  - netframework-4.6\n  - netframework-4.7\n  monikers:\n  - netframework-4.5.1\n  - netframework-4.5.2\n  - netframework-4.5\n  - netframework-4.6.1\n  - netframework-4.6.2\n  - netframework-4.6\n  - netframework-4.7\n  content_git_url: https://github.com/dotnet/docs/blob/master/xml/System.Web.UI.WebControls/SiteMapDataSourceView.xml\n  ms.technology:\n  - dotnet-webforms\n  ms.author: riande\n  manager: wpickett\n- uid: System.Web.UI.WebControls.SiteMapDataSourceView.#ctor(System.Web.UI.WebControls.SiteMapDataSource,System.String,System.Web.SiteMapNodeCollection)\n  commentId: M:System.Web.UI.WebControls.SiteMapDataSourceView.#ctor(System.Web.UI.WebControls.SiteMapDataSource,System.String,System.Web.SiteMapNodeCollection)\n  id: '#ctor(System.Web.UI.WebControls.SiteMapDataSource,System.String,System.Web.SiteMapNodeCollection)'\n  parent: System.Web.UI.WebControls.SiteMapDataSourceView\n  langs:\n  - csharp\n  name: SiteMapDataSourceView(SiteMapDataSource, String, SiteMapNodeCollection)\n  nameWithType: SiteMapDataSourceView.SiteMapDataSourceView(SiteMapDataSource, String, SiteMapNodeCollection)\n  fullName: SiteMapDataSourceView.SiteMapDataSourceView(SiteMapDataSource, String, SiteMapNodeCollection)\n  type: Constructor\n  assemblies:\n  - System.Web\n  namespace: System.Web.UI.WebControls\n  summary: Initializes a new named instance of the <xref href=\"System.Web.UI.WebControls.SiteMapDataSourceView\"></xref> class, setting the internal collection of nodes to the specified node collection.\n  remarks: The <xref:System.Web.UI.WebControls.SiteMapDataSourceView> class is a wrapper class on a <xref:System.Web.SiteMapNodeCollection> object. Creating a <xref:System.Web.UI.WebControls.SiteMapDataSourceView> using the <xref:System.Web.UI.WebControls.SiteMapDataSourceView.%23ctor%2A> constructor initializes the internal node collection with the <xref:System.Web.SiteMapNodeCollection> that is passed to the constructor.\n  syntax:\n    content: public SiteMapDataSourceView (System.Web.UI.WebControls.SiteMapDataSource owner, string name, System.Web.SiteMapNodeCollection collection);\n    parameters:\n    - id: owner\n      type: System.Web.UI.WebControls.SiteMapDataSource\n      description: The <xref href=\"System.Web.UI.WebControls.SiteMapDataSource\"></xref> that the <xref href=\"System.Web.UI.WebControls.SiteMapDataSourceView\"></xref> is associated with.\n    - id: name\n      type: System.String\n      description: The name of the view.\n    - id: collection\n      type: System.Web.SiteMapNodeCollection\n      description: A <xref href=\"System.Web.SiteMapNodeCollection\"></xref> of nodes that the <xref href=\"System.Web.UI.WebControls.SiteMapDataSourceView\"></xref> provides a view of.\n  overload: System.Web.UI.WebControls.SiteMapDataSourceView.#ctor*\n  exceptions: []\n  version:\n  - netframework-4.5.1\n  - netframework-4.5.2\n  - netframework-4.5\n  - netframework-4.6.1\n  - netframework-4.6.2\n  - netframework-4.6\n  - netframework-4.7\n  monikers:\n  - netframework-4.5.1\n  - netframework-4.5.2\n  - netframework-4.5\n  - netframework-4.6.1\n  - netframework-4.6.2\n  - netframework-4.6\n  - netframework-4.7\n  content_git_url: https://github.com/dotnet/docs/blob/master/xml/System.Web.UI.WebControls/SiteMapDataSourceView.xml\n  ms.technology:\n  - dotnet-webforms\n  ms.author: riande\n  manager: wpickett\n- uid: System.Web.UI.WebControls.SiteMapDataSourceView.ExecuteSelect(System.Web.UI.DataSourceSelectArguments)\n  commentId: M:System.Web.UI.WebControls.SiteMapDataSourceView.ExecuteSelect(System.Web.UI.DataSourceSelectArguments)\n  id: ExecuteSelect(System.Web.UI.DataSourceSelectArguments)\n  parent: System.Web.UI.WebControls.SiteMapDataSourceView\n  langs:\n  - csharp\n  name: ExecuteSelect(DataSourceSelectArguments)\n  nameWithType: SiteMapDataSourceView.ExecuteSelect(DataSourceSelectArguments)\n  fullName: SiteMapDataSourceView.ExecuteSelect(DataSourceSelectArguments)\n  type: Method\n  assemblies:\n  - System.Web\n  namespace: System.Web.UI.WebControls\n  summary: Gets the collection of the <xref href=\"System.Web.SiteMapNode\"></xref> objects that represents the site navigation structure for the current user.\n  remarks: The <xref:System.Web.UI.WebControls.SiteMapDataSourceView> class implements the inherited <xref:System.Web.UI.WebControls.SiteMapDataSourceView.ExecuteSelect%2A> method to retrieve a set of nodes that represents the site navigation structure for the current ASP.NET application. Page developers and data-bound control authors do not call the <xref:System.Web.UI.WebControls.SiteMapDataSourceView.ExecuteSelect%2A> method directly; instead, use the publicly exposed <xref:System.Web.UI.WebControls.SiteMapDataSourceView.Select%2A> method.\n  syntax:\n    content: protected override System.Collections.IEnumerable ExecuteSelect (System.Web.UI.DataSourceSelectArguments arguments);\n    parameters:\n    - id: arguments\n      type: System.Web.UI.DataSourceSelectArguments\n      description: A <xref href=\"System.Web.UI.DataSourceSelectArguments\"></xref> that is used to request operations on the data beyond basic data retrieval.\n    return:\n      type: System.Collections.IEnumerable\n      description: A <xref href=\"System.Web.SiteMapNodeCollection\"></xref> that represents the site navigation structure for the current user.\n  overload: System.Web.UI.WebControls.SiteMapDataSourceView.ExecuteSelect*\n  exceptions:\n  - type: System.NotSupportedException\n    commentId: T:System.NotSupportedException\n    description: The <code>arguments</code> passed to the <xref href=\"System.Web.UI.WebControls.SiteMapDataSourceView.Select(System.Web.UI.DataSourceSelectArguments)\"></xref> specify that the data source should perform some additional work while retrieving data to enable paging or sorting through the retrieved data, but the data source control does not support the requested capability.\n  version:\n  - netframework-4.5.1\n  - netframework-4.5.2\n  - netframework-4.5\n  - netframework-4.6.1\n  - netframework-4.6.2\n  - netframework-4.6\n  - netframework-4.7\n  monikers:\n  - netframework-4.5.1\n  - netframework-4.5.2\n  - netframework-4.5\n  - netframework-4.6.1\n  - netframework-4.6.2\n  - netframework-4.6\n  - netframework-4.7\n  content_git_url: https://github.com/dotnet/docs/blob/master/xml/System.Web.UI.WebControls/SiteMapDataSourceView.xml\n  ms.technology:\n  - dotnet-webforms\n  ms.author: riande\n  manager: wpickett\n- uid: System.Web.UI.WebControls.SiteMapDataSourceView.OnDataSourceViewChanged(System.EventArgs)\n  commentId: M:System.Web.UI.WebControls.SiteMapDataSourceView.OnDataSourceViewChanged(System.EventArgs)\n  id: OnDataSourceViewChanged(System.EventArgs)\n  parent: System.Web.UI.WebControls.SiteMapDataSourceView\n  langs:\n  - csharp\n  name: OnDataSourceViewChanged(EventArgs)\n  nameWithType: SiteMapDataSourceView.OnDataSourceViewChanged(EventArgs)\n  fullName: SiteMapDataSourceView.OnDataSourceViewChanged(EventArgs)\n  type: Method\n  assemblies:\n  - System.Web\n  namespace: System.Web.UI.WebControls\n  summary: Raises the <xref href=\"System.Web.UI.DataSourceView.DataSourceViewChanged\"></xref> event.\n  syntax:\n    content: protected override void OnDataSourceViewChanged (EventArgs e);\n    parameters:\n    - id: e\n      type: System.EventArgs\n      description: An <xref href=\"System.EventArgs\"></xref> that contains event data.\n  overload: System.Web.UI.WebControls.SiteMapDataSourceView.OnDataSourceViewChanged*\n  exceptions: []\n  version:\n  - netframework-4.5.1\n  - netframework-4.5.2\n  - netframework-4.5\n  - netframework-4.6.1\n  - netframework-4.6.2\n  - netframework-4.6\n  - netframework-4.7\n  monikers:\n  - netframework-4.5.1\n  - netframework-4.5.2\n  - netframework-4.5\n  - netframework-4.6.1\n  - netframework-4.6.2\n  - netframework-4.6\n  - netframework-4.7\n  content_git_url: https://github.com/dotnet/docs/blob/master/xml/System.Web.UI.WebControls/SiteMapDataSourceView.xml\n  ms.technology:\n  - dotnet-webforms\n  ms.author: riande\n  manager: wpickett\n- uid: System.Web.UI.WebControls.SiteMapDataSourceView.Select(System.Web.UI.DataSourceSelectArguments)\n  commentId: M:System.Web.UI.WebControls.SiteMapDataSourceView.Select(System.Web.UI.DataSourceSelectArguments)\n  id: Select(System.Web.UI.DataSourceSelectArguments)\n  parent: System.Web.UI.WebControls.SiteMapDataSourceView\n  langs:\n  - csharp\n  name: Select(DataSourceSelectArguments)\n  nameWithType: SiteMapDataSourceView.Select(DataSourceSelectArguments)\n  fullName: SiteMapDataSourceView.Select(DataSourceSelectArguments)\n  type: Method\n  assemblies:\n  - System.Web\n  namespace: System.Web.UI.WebControls\n  summary: Gets the collection of the <xref href=\"System.Web.SiteMapNode\"></xref> objects that represents the site navigation structure for the current user.\n  remarks: The <xref:System.Web.UI.WebControls.SiteMapDataSourceView.Select%2A> method calls the <xref:System.Web.UI.WebControls.SiteMapDataSourceView.ExecuteSelect%2A> method, passing the `arguments` parameter. The <xref:System.Web.UI.WebControls.SiteMapDataSourceView.Select%2A> method is used by controls developers but it is not used by page developers nor in page code.\n  syntax:\n    content: public System.Collections.IEnumerable Select (System.Web.UI.DataSourceSelectArguments arguments);\n    parameters:\n    - id: arguments\n      type: System.Web.UI.DataSourceSelectArguments\n      description: A <xref href=\"System.Web.UI.DataSourceSelectArguments\"></xref> that is used to request operations on the data beyond basic data retrieval.\n    return:\n      type: System.Collections.IEnumerable\n      description: A <xref href=\"System.Web.SiteMapNodeCollection\"></xref> that represents the site navigation structure for the current user.\n  overload: System.Web.UI.WebControls.SiteMapDataSourceView.Select*\n  exceptions:\n  - type: System.NotSupportedException\n    commentId: T:System.NotSupportedException\n    description: The <code>arguments</code> passed to the <xref href=\"System.Web.UI.WebControls.SiteMapDataSourceView.Select(System.Web.UI.DataSourceSelectArguments)\"></xref> specify that the data source should perform some additional work while retrieving data to enable paging or sorting through the retrieved data, but the data source control does not support the requested capability.\n  version:\n  - netframework-4.5.1\n  - netframework-4.5.2\n  - netframework-4.5\n  - netframework-4.6.1\n  - netframework-4.6.2\n  - netframework-4.6\n  - netframework-4.7\n  monikers:\n  - netframework-4.5.1\n  - netframework-4.5.2\n  - netframework-4.5\n  - netframework-4.6.1\n  - netframework-4.6.2\n  - netframework-4.6\n  - netframework-4.7\n  content_git_url: https://github.com/dotnet/docs/blob/master/xml/System.Web.UI.WebControls/SiteMapDataSourceView.xml\n  ms.technology:\n  - dotnet-webforms\n  ms.author: riande\n  manager: wpickett\nreferences:\n- uid: System.Web.UI.DataSourceView\n  parent: System.Web.UI\n  isExternal: false\n  name: DataSourceView\n  nameWithType: DataSourceView\n  fullName: System.Web.UI.DataSourceView\n- uid: System.NotSupportedException\n  parent: System\n  isExternal: false\n  name: NotSupportedException\n  nameWithType: NotSupportedException\n  fullName: System.NotSupportedException\n- uid: System.Web.UI.WebControls.SiteMapDataSourceView.#ctor(System.Web.UI.WebControls.SiteMapDataSource,System.String,System.Web.SiteMapNode)\n  parent: System.Web.UI.WebControls.SiteMapDataSourceView\n  isExternal: false\n  name: SiteMapDataSourceView(SiteMapDataSource, String, SiteMapNode)\n  nameWithType: SiteMapDataSourceView.SiteMapDataSourceView(SiteMapDataSource, String, SiteMapNode)\n  fullName: SiteMapDataSourceView.SiteMapDataSourceView(SiteMapDataSource, String, SiteMapNode)\n- uid: System.Web.UI.WebControls.SiteMapDataSource\n  parent: System.Web.UI.WebControls\n  isExternal: false\n  name: SiteMapDataSource\n  nameWithType: SiteMapDataSource\n  fullName: System.Web.UI.WebControls.SiteMapDataSource\n- uid: System.String\n  parent: System\n  isExternal: false\n  name: String\n  nameWithType: String\n  fullName: System.String\n- uid: System.Web.SiteMapNode\n  parent: System.Web\n  isExternal: false\n  name: SiteMapNode\n  nameWithType: SiteMapNode\n  fullName: System.Web.SiteMapNode\n- uid: System.Web.UI.WebControls.SiteMapDataSourceView.#ctor(System.Web.UI.WebControls.SiteMapDataSource,System.String,System.Web.SiteMapNodeCollection)\n  parent: System.Web.UI.WebControls.SiteMapDataSourceView\n  isExternal: false\n  name: SiteMapDataSourceView(SiteMapDataSource, String, SiteMapNodeCollection)\n  nameWithType: SiteMapDataSourceView.SiteMapDataSourceView(SiteMapDataSource, String, SiteMapNodeCollection)\n  fullName: SiteMapDataSourceView.SiteMapDataSourceView(SiteMapDataSource, String, SiteMapNodeCollection)\n- uid: System.Web.SiteMapNodeCollection\n  parent: System.Web\n  isExternal: false\n  name: SiteMapNodeCollection\n  nameWithType: SiteMapNodeCollection\n  fullName: System.Web.SiteMapNodeCollection\n- uid: System.Web.UI.WebControls.SiteMapDataSourceView.ExecuteSelect(System.Web.UI.DataSourceSelectArguments)\n  parent: System.Web.UI.WebControls.SiteMapDataSourceView\n  isExternal: false\n  name: ExecuteSelect(DataSourceSelectArguments)\n  nameWithType: SiteMapDataSourceView.ExecuteSelect(DataSourceSelectArguments)\n  fullName: SiteMapDataSourceView.ExecuteSelect(DataSourceSelectArguments)\n- uid: System.Collections.IEnumerable\n  parent: System.Collections\n  isExternal: false\n  name: IEnumerable\n  nameWithType: IEnumerable\n  fullName: System.Collections.IEnumerable\n- uid: System.Web.UI.DataSourceSelectArguments\n  parent: System.Web.UI\n  isExternal: false\n  name: DataSourceSelectArguments\n  nameWithType: DataSourceSelectArguments\n  fullName: System.Web.UI.DataSourceSelectArguments\n- uid: System.Web.UI.WebControls.SiteMapDataSourceView.OnDataSourceViewChanged(System.EventArgs)\n  parent: System.Web.UI.WebControls.SiteMapDataSourceView\n  isExternal: false\n  name: OnDataSourceViewChanged(EventArgs)\n  nameWithType: SiteMapDataSourceView.OnDataSourceViewChanged(EventArgs)\n  fullName: SiteMapDataSourceView.OnDataSourceViewChanged(EventArgs)\n- uid: System.EventArgs\n  parent: System\n  isExternal: false\n  name: EventArgs\n  nameWithType: EventArgs\n  fullName: System.EventArgs\n- uid: System.Web.UI.WebControls.SiteMapDataSourceView.Select(System.Web.UI.DataSourceSelectArguments)\n  parent: System.Web.UI.WebControls.SiteMapDataSourceView\n  isExternal: false\n  name: Select(DataSourceSelectArguments)\n  nameWithType: SiteMapDataSourceView.Select(DataSourceSelectArguments)\n  fullName: SiteMapDataSourceView.Select(DataSourceSelectArguments)\n- uid: System.Web.UI.WebControls.SiteMapDataSourceView.#ctor*\n  parent: System.Web.UI.WebControls.SiteMapDataSourceView\n  isExternal: false\n  name: SiteMapDataSourceView\n  nameWithType: SiteMapDataSourceView.SiteMapDataSourceView\n  fullName: SiteMapDataSourceView.SiteMapDataSourceView\n  monikers:\n  - netframework-4.5.1\n  - netframework-4.5.2\n  - netframework-4.5\n  - netframework-4.6.1\n  - netframework-4.6.2\n  - netframework-4.6\n  - netframework-4.7\n  content_git_url: https://github.com/dotnet/docs/blob/master/xml/System.Web.UI.WebControls/SiteMapDataSourceView.xml\n- uid: System.Web.UI.WebControls.SiteMapDataSourceView.ExecuteSelect*\n  parent: System.Web.UI.WebControls.SiteMapDataSourceView\n  isExternal: false\n  name: ExecuteSelect\n  nameWithType: SiteMapDataSourceView.ExecuteSelect\n  fullName: SiteMapDataSourceView.ExecuteSelect\n  monikers:\n  - netframework-4.5.1\n  - netframework-4.5.2\n  - netframework-4.5\n  - netframework-4.6.1\n  - netframework-4.6.2\n  - netframework-4.6\n  - netframework-4.7\n  content_git_url: https://github.com/dotnet/docs/blob/master/xml/System.Web.UI.WebControls/SiteMapDataSourceView.xml\n- uid: System.Web.UI.WebControls.SiteMapDataSourceView.OnDataSourceViewChanged*\n  parent: System.Web.UI.WebControls.SiteMapDataSourceView\n  isExternal: false\n  name: OnDataSourceViewChanged\n  nameWithType: SiteMapDataSourceView.OnDataSourceViewChanged\n  fullName: SiteMapDataSourceView.OnDataSourceViewChanged\n  monikers:\n  - netframework-4.5.1\n  - netframework-4.5.2\n  - netframework-4.5\n  - netframework-4.6.1\n  - netframework-4.6.2\n  - netframework-4.6\n  - netframework-4.7\n  content_git_url: https://github.com/dotnet/docs/blob/master/xml/System.Web.UI.WebControls/SiteMapDataSourceView.xml\n- uid: System.Web.UI.WebControls.SiteMapDataSourceView.Select*\n  parent: System.Web.UI.WebControls.SiteMapDataSourceView\n  isExternal: false\n  name: Select\n  nameWithType: SiteMapDataSourceView.Select\n  fullName: SiteMapDataSourceView.Select\n  monikers:\n  - netframework-4.5.1\n  - netframework-4.5.2\n  - netframework-4.5\n  - netframework-4.6.1\n  - netframework-4.6.2\n  - netframework-4.6\n  - netframework-4.7\n  content_git_url: https://github.com/dotnet/docs/blob/master/xml/System.Web.UI.WebControls/SiteMapDataSourceView.xml\n- uid: System.Object.Equals(System.Object)\n  parent: System.Object\n  isExternal: false\n  name: Equals(Object)\n  nameWithType: Object.Equals(Object)\n  fullName: Object.Equals(Object)\n- uid: System.Object.Equals(System.Object,System.Object)\n  parent: System.Object\n  isExternal: false\n  name: Equals(Object, Object)\n  nameWithType: Object.Equals(Object, Object)\n  fullName: Object.Equals(Object, Object)\n- uid: System.Object.GetHashCode\n  parent: System.Object\n  isExternal: false\n  name: GetHashCode()\n  nameWithType: Object.GetHashCode()\n  fullName: Object.GetHashCode()\n- uid: System.Object.GetType\n  parent: System.Object\n  isExternal: false\n  name: GetType()\n  nameWithType: Object.GetType()\n  fullName: Object.GetType()\n- uid: System.Object.MemberwiseClone\n  parent: System.Object\n  isExternal: false\n  name: MemberwiseClone()\n  nameWithType: Object.MemberwiseClone()\n  fullName: Object.MemberwiseClone()\n- uid: System.Object.ReferenceEquals(System.Object,System.Object)\n  parent: System.Object\n  isExternal: false\n  name: ReferenceEquals(Object, Object)\n  nameWithType: Object.ReferenceEquals(Object, Object)\n  fullName: Object.ReferenceEquals(Object, Object)\n- uid: System.Object.ToString\n  parent: System.Object\n  isExternal: false\n  name: ToString()\n  nameWithType: Object.ToString()\n  fullName: Object.ToString()\n- uid: System.Web.UI.DataSourceView.CanDelete\n  parent: System.Web.UI.DataSourceView\n  isExternal: false\n  name: CanDelete\n  nameWithType: DataSourceView.CanDelete\n  fullName: DataSourceView.CanDelete\n- uid: System.Web.UI.DataSourceView.CanExecute(System.String)\n  parent: System.Web.UI.DataSourceView\n  isExternal: false\n  name: CanExecute(String)\n  nameWithType: DataSourceView.CanExecute(String)\n  fullName: DataSourceView.CanExecute(String)\n- uid: System.Web.UI.DataSourceView.CanInsert\n  parent: System.Web.UI.DataSourceView\n  isExternal: false\n  name: CanInsert\n  nameWithType: DataSourceView.CanInsert\n  fullName: DataSourceView.CanInsert\n- uid: System.Web.UI.DataSourceView.CanPage\n  parent: System.Web.UI.DataSourceView\n  isExternal: false\n  name: CanPage\n  nameWithType: DataSourceView.CanPage\n  fullName: DataSourceView.CanPage\n- uid: System.Web.UI.DataSourceView.CanRetrieveTotalRowCount\n  parent: System.Web.UI.DataSourceView\n  isExternal: false\n  name: CanRetrieveTotalRowCount\n  nameWithType: DataSourceView.CanRetrieveTotalRowCount\n  fullName: DataSourceView.CanRetrieveTotalRowCount\n- uid: System.Web.UI.DataSourceView.CanSort\n  parent: System.Web.UI.DataSourceView\n  isExternal: false\n  name: CanSort\n  nameWithType: DataSourceView.CanSort\n  fullName: DataSourceView.CanSort\n- uid: System.Web.UI.DataSourceView.CanUpdate\n  parent: System.Web.UI.DataSourceView\n  isExternal: false\n  name: CanUpdate\n  nameWithType: DataSourceView.CanUpdate\n  fullName: DataSourceView.CanUpdate\n- uid: System.Web.UI.DataSourceView.DataSourceViewChanged\n  parent: System.Web.UI.DataSourceView\n  isExternal: false\n  name: DataSourceViewChanged\n  nameWithType: DataSourceView.DataSourceViewChanged\n  fullName: DataSourceView.DataSourceViewChanged\n- uid: System.Web.UI.DataSourceView.Delete(System.Collections.IDictionary,System.Collections.IDictionary,System.Web.UI.DataSourceViewOperationCallback)\n  parent: System.Web.UI.DataSourceView\n  isExternal: false\n  name: Delete(IDictionary, IDictionary, DataSourceViewOperationCallback)\n  nameWithType: DataSourceView.Delete(IDictionary, IDictionary, DataSourceViewOperationCallback)\n  fullName: DataSourceView.Delete(IDictionary, IDictionary, DataSourceViewOperationCallback)\n- uid: System.Web.UI.DataSourceView.Events\n  parent: System.Web.UI.DataSourceView\n  isExternal: false\n  name: Events\n  nameWithType: DataSourceView.Events\n  fullName: DataSourceView.Events\n- uid: System.Web.UI.DataSourceView.ExecuteCommand(System.String,System.Collections.IDictionary,System.Collections.IDictionary,System.Web.UI.DataSourceViewOperationCallback)\n  parent: System.Web.UI.DataSourceView\n  isExternal: false\n  name: ExecuteCommand(String, IDictionary, IDictionary, DataSourceViewOperationCallback)\n  nameWithType: DataSourceView.ExecuteCommand(String, IDictionary, IDictionary, DataSourceViewOperationCallback)\n  fullName: DataSourceView.ExecuteCommand(String, IDictionary, IDictionary, DataSourceViewOperationCallback)\n- uid: System.Web.UI.DataSourceView.ExecuteCommand(System.String,System.Collections.IDictionary,System.Collections.IDictionary)\n  parent: System.Web.UI.DataSourceView\n  isExternal: false\n  name: ExecuteCommand(String, IDictionary, IDictionary)\n  nameWithType: DataSourceView.ExecuteCommand(String, IDictionary, IDictionary)\n  fullName: DataSourceView.ExecuteCommand(String, IDictionary, IDictionary)\n- uid: System.Web.UI.DataSourceView.ExecuteDelete(System.Collections.IDictionary,System.Collections.IDictionary)\n  parent: System.Web.UI.DataSourceView\n  isExternal: false\n  name: ExecuteDelete(IDictionary, IDictionary)\n  nameWithType: DataSourceView.ExecuteDelete(IDictionary, IDictionary)\n  fullName: DataSourceView.ExecuteDelete(IDictionary, IDictionary)\n- uid: System.Web.UI.DataSourceView.ExecuteInsert(System.Collections.IDictionary)\n  parent: System.Web.UI.DataSourceView\n  isExternal: false\n  name: ExecuteInsert(IDictionary)\n  nameWithType: DataSourceView.ExecuteInsert(IDictionary)\n  fullName: DataSourceView.ExecuteInsert(IDictionary)\n- uid: System.Web.UI.DataSourceView.ExecuteUpdate(System.Collections.IDictionary,System.Collections.IDictionary,System.Collections.IDictionary)\n  parent: System.Web.UI.DataSourceView\n  isExternal: false\n  name: ExecuteUpdate(IDictionary, IDictionary, IDictionary)\n  nameWithType: DataSourceView.ExecuteUpdate(IDictionary, IDictionary, IDictionary)\n  fullName: DataSourceView.ExecuteUpdate(IDictionary, IDictionary, IDictionary)\n- uid: System.Web.UI.DataSourceView.Insert(System.Collections.IDictionary,System.Web.UI.DataSourceViewOperationCallback)\n  parent: System.Web.UI.DataSourceView\n  isExternal: false\n  name: Insert(IDictionary, DataSourceViewOperationCallback)\n  nameWithType: DataSourceView.Insert(IDictionary, DataSourceViewOperationCallback)\n  fullName: DataSourceView.Insert(IDictionary, DataSourceViewOperationCallback)\n- uid: System.Web.UI.DataSourceView.Name\n  parent: System.Web.UI.DataSourceView\n  isExternal: false\n  name: Name\n  nameWithType: DataSourceView.Name\n  fullName: DataSourceView.Name\n- uid: System.Web.UI.DataSourceView.RaiseUnsupportedCapabilityError(System.Web.UI.DataSourceCapabilities)\n  parent: System.Web.UI.DataSourceView\n  isExternal: false\n  name: RaiseUnsupportedCapabilityError(DataSourceCapabilities)\n  nameWithType: DataSourceView.RaiseUnsupportedCapabilityError(DataSourceCapabilities)\n  fullName: DataSourceView.RaiseUnsupportedCapabilityError(DataSourceCapabilities)\n- uid: System.Web.UI.DataSourceView.Select(System.Web.UI.DataSourceSelectArguments,System.Web.UI.DataSourceViewSelectCallback)\n  parent: System.Web.UI.DataSourceView\n  isExternal: false\n  name: Select(DataSourceSelectArguments, DataSourceViewSelectCallback)\n  nameWithType: DataSourceView.Select(DataSourceSelectArguments, DataSourceViewSelectCallback)\n  fullName: DataSourceView.Select(DataSourceSelectArguments, DataSourceViewSelectCallback)\n- uid: System.Web.UI.DataSourceView.Update(System.Collections.IDictionary,System.Collections.IDictionary,System.Collections.IDictionary,System.Web.UI.DataSourceViewOperationCallback)\n  parent: System.Web.UI.DataSourceView\n  isExternal: false\n  name: Update(IDictionary, IDictionary, IDictionary, DataSourceViewOperationCallback)\n  nameWithType: DataSourceView.Update(IDictionary, IDictionary, IDictionary, DataSourceViewOperationCallback)\n  fullName: DataSourceView.Update(IDictionary, IDictionary, IDictionary, DataSourceViewOperationCallback)\n"}